pydantic_lambda_handler/__init__.py
pydantic_lambda_handler/gen_open_api_inspect.py
pydantic_lambda_handler/main.py
pydantic_lambda_handler/middleware.py
pydantic_lambda_handler/models.py
pydantic_lambda_handler/params.py
pydantic_lambda_handler/responses.py
pydantic_lambda_handler/hooks/cdk_conf_hook.py
pydantic_lambda_handler/hooks/mock_requests.py
pydantic_lambda_handler/hooks/open_api_gen_hook.py
pydantic_lambda_handler-1.0.1.dist-info/entry_points.txt
pydantic_lambda_handler-1.0.1.dist-info/LICENSE
pydantic_lambda_handler-1.0.1.dist-info/WHEEL
pydantic_lambda_handler-1.0.1.dist-info/METADATA
pydantic_lambda_handler-1.0.1.dist-info/RECORD
