Metadata-Version: 2.1
Name: pydantic_lambda_handler
Version: 1.0.1
Summary: Pydantic lambda handler modelled on FastAPI
Author-email: Mark Harvey <inspiredharvey@gmail.com>
Classifier: License :: OSI Approved :: MIT License
Requires-Dist: pydantic>=2.0.0
Requires-Dist: openapi-pydantic
Requires-Dist: orjson>=3.7.5
Requires-Dist: coverage>=5.0.3 ; extra == "dev"
Requires-Dist: pytest ; extra == "dev"
Requires-Dist: pytest-benchmark[histogram]>=3.2.1 ; extra == "dev"
Requires-Dist: aws-cdk-lib ; extra == "dev"
Requires-Dist: requests ; extra == "dev"
Requires-Dist: invoke ; extra == "dev"
Requires-Dist: awslambdaric ; extra == "dev"
Requires-Dist: boto3>=1.20.32 ; extra == "dev"
Requires-Dist: botocore>=1.23.32 ; extra == "dev"
Requires-Dist: openapi-schema-pydantic ; extra == "dev"
Requires-Dist: pytest ; extra == "tests"
Requires-Dist: pytest-cov ; extra == "tests"
Requires-Dist: pytest-mock ; extra == "tests"
Requires-Dist: requests ; extra == "tests"
Requires-Dist: awslambdaric ; extra == "tests"
Requires-Dist: boto3>=1.20.32 ; extra == "tests"
Requires-Dist: botocore>=1.23.32 ; extra == "tests"
Requires-Dist: openapi-spec-validator ; extra == "tests"
Requires-Dist: pydantic-core ; extra == "tests"
Project-URL: Home, https://github.com/harvey251/pydantic-lambda-handler
Provides-Extra: dev
Provides-Extra: tests
